pip_licenses_lib-1.0.0.dist-info/licenses/LICENSE.txt
piplicenses_lib/__init__.py
piplicenses_lib/py.typed
pip_licenses_lib-1.0.0.dist-info/METADATA
pip_licenses_lib-1.0.0.dist-info/WHEEL
pip_licenses_lib-1.0.0.dist-info/top_level.txt
pip_licenses_lib-1.0.0.dist-info/RECORD
